{
    "common": {
        "play": "Играть",
        "shop": "Магазин",
        "settings": "Настройки",
        "quit": "Выход",
        "back": "Назад",
        "coins": "Монеты",
        "hints": "Подсказки",
        "time": "Время",
        "score": "Очки",
        "level": "Уровень",
        "next": "Далее",
        "retry": "Повторить",
        "pause": "Пауза",
        "resume": "Продолжить",
        "restart": "Начать заново",
        "main_menu": "Главное меню",
        "loading": "Загрузка...",
        "error": "Ошибка",
        "success": "Успех",
        "failed": "Неудача",
        "perfect": "Отлично!",
        "good": "Хорошо",
        "bad": "Плохо"
    },
    "modes": {
        "mystery_story": "Загадочная История",
        "photofit": "Фоторобот",
        "crime_scene": "Место Преступления",
        "expertise": "Экспертиза"
    },
    "settings": {
        "sound": "Звук",
        "music": "Музыка",
        "sfx": "Эффекты",
        "graphics": "Графика",
        "quality": "Качество",
        "fullscreen": "Полный экран",
        "language": "Язык",
        "difficulty": "Сложность",
        "easy": "Легкий",
        "normal": "Средний",
        "hard": "Сложный",
        "tutorial": "Обучение"
    },
    "shop": {
        "coins_pack_small": "Малый набор монет",
        "coins_pack_medium": "Средний набор монет",
        "coins_pack_large": "Большой набор монет",
        "hints_pack_small": "Малый набор подсказок",
        "hints_pack_medium": "Средний набор подсказок",
        "hints_pack_large": "Большой набор подсказок",
        "remove_ads": "Убрать рекламу",
        "buy": "Купить",
        "not_enough_coins": "Недостаточно монет",
        "purchase_success": "Покупка успешна",
        "purchase_failed": "Ошибка покупки"
    },
    "achievements": {
        "words_master": "Мастер слов",
        "words_master_desc": "Составьте 100 слов",
        "level_master": "Мастер уровней",
        "level_master_desc": "Пройдите 50 уровней",
        "coins_collector": "Собиратель монет",
        "coins_collector_desc": "Соберите 1000 монет",
        "hints_master": "Мастер подсказок",
        "hints_master_desc": "Используйте 50 подсказок",
        "unlocked": "Достижение разблокировано!",
        "locked": "Достижение заблокировано"
    },
    "tutorial": {
        "welcome": "Добро пожаловать в Словесный Детектив!",
        "intro": "В этой игре вам предстоит разгадывать загадки с помощью слов.",
        "modes": "Выберите режим игры:",
        "mystery_story": "В режиме 'Загадочная История' вы будете читать истории и выбирать правильные слова.",
        "photofit": "В режиме 'Фоторобот' составляйте слова, чтобы создать портрет подозреваемого.",
        "crime_scene": "В режиме 'Место Преступления' ищите улики и описывайте их словами.",
        "expertise": "В режиме 'Экспертиза' проводите анализ и составляйте отчеты.",
        "coins": "Зарабатывайте монеты за успешное прохождение уровней.",
        "hints": "Используйте подсказки, если застряли.",
        "shop": "В магазине вы можете купить монеты и подсказки.",
        "settings": "Настройте игру под себя в меню настроек.",
        "good_luck": "Удачи в расследованиях!"
    }
} 